fireworks_schema/__init__.py
fireworks_schema/json_schema.py
fireworks_schema/schema/addfilestask.json
fireworks_schema/schema/archivedirtask.json
fireworks_schema/schema/backgroundtask.json
fireworks_schema/schema/commandlinetask.json
fireworks_schema/schema/commonadapter.json
fireworks_schema/schema/compressdirtask.json
fireworks_schema/schema/deletefilestask.json
fireworks_schema/schema/dupefinder.json
fireworks_schema/schema/exporttestserializer.json
fireworks_schema/schema/filedeletetask.json
fireworks_schema/schema/filetransfertask.json
fireworks_schema/schema/filewritetask.json
fireworks_schema/schema/firetask.json
fireworks_schema/schema/firework.json
fireworks_schema/schema/foreachtask.json
fireworks_schema/schema/fwaction.json
fireworks_schema/schema/fwconfig.json
fireworks_schema/schema/fworker.json
fireworks_schema/schema/generic.json
fireworks_schema/schema/getfilestask.json
fireworks_schema/schema/importdatatask.json
fireworks_schema/schema/joindicttask.json
fireworks_schema/schema/joinlisttask.json
fireworks_schema/schema/launch.json
fireworks_schema/schema/launchpad.json
fireworks_schema/schema/links.json
fireworks_schema/schema/pytask.json
fireworks_schema/schema/scripttask.json
fireworks_schema/schema/spec.json
fireworks_schema/schema/templatewritertask.json
fireworks_schema/schema/testserializer.json
fireworks_schema/schema/tracker.json
fireworks_schema/schema/workflow.json
fireworks_schema-1.4.2.dist-info/licenses/LICENSE
fireworks_schema-1.4.2.dist-info/METADATA
fireworks_schema-1.4.2.dist-info/WHEEL
fireworks_schema-1.4.2.dist-info/top_level.txt
fireworks_schema-1.4.2.dist-info/RECORD
