Metadata-Version: 2.4
Name: fireworks-schema
Version: 1.4.2
Summary: JSON Schema for FireWorks
Author: Ivan Kondov
Author-email: ivan.kondov@kit.edu
License: BSD-3-Clause
Project-URL: Homepage, https://github.com/ikondov/fireworks_schema
Project-URL: Download, https://pypi.org/project/fireworks-schema/#files
Project-URL: Source Code, https://github.com/ikondov/fireworks_schema
Project-URL: Bug Reports, https://github.com/ikondov/fireworks_schema/issues
Keywords: workflow system,json schema,fireworks
Classifier: Programming Language :: Python
Classifier: Programming Language :: Python :: 3
Classifier: Development Status :: 4 - Beta
Classifier: Intended Audience :: Science/Research
Classifier: Intended Audience :: System Administrators
Classifier: Intended Audience :: Information Technology
Classifier: Operating System :: OS Independent
Classifier: Topic :: Other/Nonlisted Topic
Classifier: Topic :: Scientific/Engineering
Requires-Python: >=3.6
License-File: LICENSE
Requires-Dist: jsonschema>=4.0.0
Requires-Dist: fireworks>=2.0.2
Requires-Dist: pymongo>=3.9.0
Requires-Dist: semantic-version
Provides-Extra: test
Requires-Dist: pytest; extra == "test"
Dynamic: license-file
